fabricpy/__init__.py
fabricpy/__version__.py
fabricpy/block.py
fabricpy/fooditem.py
fabricpy/item.py
fabricpy/item_group.py
fabricpy/itemgroup.py
fabricpy/modconfig.py
fabricpy/recipejson.py
fabricpy-0.1.3.dist-info/licenses/LICENSE
fabricpy-0.1.3.dist-info/METADATA
fabricpy-0.1.3.dist-info/WHEEL
fabricpy-0.1.3.dist-info/top_level.txt
fabricpy-0.1.3.dist-info/RECORD
