Metadata-Version: 2.4
Name: fabricpy
Version: 0.1.3
Summary: A lightweight helper library for writing Fabric mods in Python
Home-page: https://github.com/danielkorkin/fabricpy
Download-URL: https://github.com/danielkorkin/fabricpy/archive/v0.1.3.tar.gz
Author: Daniel Korkin
Author-email: Daniel Korkin <danielkorkin@example.com>
Maintainer: Daniel Korkin
Maintainer-email: Daniel Korkin <danielkorkin@example.com>
License-Expression: MIT
Project-URL: Documentation, https://fabricpy.readthedocs.io/
Project-URL: Repository, https://github.com/danielkorkin/fabricpy
Project-URL: Bug Tracker, https://github.com/danielkorkin/fabricpy/issues
Project-URL: Coverage, https://app.codecov.io/gh/danielkorkin/fabricpy
Project-URL: Discussions, https://github.com/danielkorkin/fabricpy/discussions
Keywords: minecraft,fabric,mod,modding,game-development,java-generation,minecraft-forge,minecraft-fabric,mod-development,code-generator,python-to-java
Platform: any
Classifier: Development Status :: 4 - Beta
Classifier: Intended Audience :: Developers
Classifier: Topic :: Software Development :: Libraries :: Python Modules
Classifier: Topic :: Games/Entertainment
Classifier: Topic :: Software Development :: Code Generators
Classifier: Programming Language :: Python :: 3
Classifier: Programming Language :: Python :: 3.10
Classifier: Programming Language :: Python :: 3.11
Classifier: Programming Language :: Python :: 3.12
Classifier: Programming Language :: Java
Classifier: Operating System :: OS Independent
Classifier: Environment :: Console
Requires-Python: >=3.10
License-File: LICENSE
Provides-Extra: dev
Requires-Dist: pytest>=7.0; extra == "dev"
Requires-Dist: pytest-cov>=4.0; extra == "dev"
Requires-Dist: coverage>=6.0; extra == "dev"
Requires-Dist: pytest-mock>=3.10.0; extra == "dev"
Provides-Extra: docs
Requires-Dist: sphinx>=4.0.0; extra == "docs"
Requires-Dist: sphinx-rtd-theme; extra == "docs"
Provides-Extra: test
Requires-Dist: pytest>=7.0; extra == "test"
Requires-Dist: pytest-cov>=4.0; extra == "test"
Requires-Dist: coverage>=6.0; extra == "test"
Requires-Dist: pytest-mock>=3.10.0; extra == "test"
Dynamic: author
Dynamic: download-url
Dynamic: home-page
Dynamic: license-file
Dynamic: maintainer
Dynamic: platform
Dynamic: requires-python
